slave_timer.v
//////////////////////////////////////////////////////////////////////////////////
// Company:
// Engineer: Artem Kozhevnikov
//
// Module Name: apb_timer
// Client Project: course_job_v12
// Dependencies:
//
// Revision: 30.05.24
// Additional Comments: timer works with APB interface as a slave.
//
//////////////////////////////////////////////////////////////////////////////////

module apb_timer (
  input          pclk,
  input          preset_n,  // Active low reset   
  input          psel_o,
  input          penable_o,
  input   [31:0] paddr_o,
  input          pwrite_o,
  input   [7:0]  pwdata_o,
  output  [7:0]  prdata_i,
  output         pready_i,
  output         timeout
);
  //reg is_set; // to start listening for start/stop instructions
  reg [7:0] counter; // for timer
  reg start_stop; // start <=> 1; stop <=> 0
  reg pready_ii; // inner reg for pready_i
  reg [7:0] prdata_ii; // inner reg for predata_i
  reg is_timeout; // inner reg for timeout

  always @(posedge pclk or negedge preset_n) begin
    if (~preset_n) begin
      pready_ii <= 1'b0;
      start_stop <= 1'b0;
      counter <= 8'b0;
      //is_set <= 1'b0;
      is_timeout <= 1'b0;
    end else begin
      if (start_stop && counter > 8'b0) counter <= (counter - 1'b1); // count
      else if(counter == 8'b0 && start_stop == 1'b1) is_timeout <= 1'b1; // send 1 when completed
      
      if (psel_o && penable_o) begin // ACCESS
        pready_ii <= 1'b1;
        if (pwrite_o) begin  // if WRITE
          if(paddr_o == 32'hA000) begin
            counter <= pwdata_o;
            //is_set <= 1'b1;
          end else if(paddr_o == 32'hA001)
            start_stop <= pwdata_o;
        end else begin  // if READ
          prdata_ii <= counter;
        end
      end else begin
        pready_ii <= 1'b0;
      end
    end
  end
  assign pready_i = pready_ii;
  assign prdata_i = prdata_ii;
  assign timeout = is_timeout;

endmodule

master_with_tb.v
`include "slave_timer.v"
`define CLK @(posedge pclk)

//////////////////////////////////////////////////////////////////////////////////
// Company:
// Engineer: Artem Kozhevnikov
//
// Create Date: 01.05.2024 
// Module Name: apb_master_tb
// Project Name: course_job_v12
// Revision: 30.05.2024
// Additional Comments: master initiates transactions inside this testbench.
//
//////////////////////////////////////////////////////////////////////////////////


module apb_master_tb ();
  // I/O
  reg           pclk;
  reg           preset_n;   // Active low reset
  reg  [1:0]    add_i;      // 2'b00 - NOP, 2'b01 - READ, 2'b11 - WRITE - NOT IO!!!
  wire          psel_o;
  wire          penable_o;
  wire [31:0]   paddr_o;
  wire          pwrite_o;
  wire  [7:0]   pwdata_o; // input to slave
  wire  [7:0]   prdata_i;
  wire          pready_i;
  wire          is_timeout;

  // inner registers
  reg [1:0] state_q, nxt_state;
  wire apb_state_setup, apb_state_access;
  reg nxt_pwrite, pwrite_q;
  reg [7:0] nxt_rdata, rdata_q;
  reg [7:0] pwdata_int; // inner register for pwdata_o
  reg [31:0]   paddr_inside; // for paddr_o
  
  // Implement clock
  always begin
    pclk = 1'b0;
    #5;
    pclk = 1'b1;
    #5;
  end

  // Instantiate the RTL
  apb_timer APB_SLAVE (
    .pclk(pclk),
    .preset_n(preset_n),
    .psel_o(psel_o),
    .penable_o(penable_o),
    .paddr_o(paddr_o),
    .pwrite_o(pwrite_o),
    .pwdata_o(pwdata_o),
    .prdata_i(prdata_i),
    .pready_i(pready_i),
    .timeout(timeout)
  );

  // Drive stimulus
  initial begin
    preset_n = 1'b0;
    pwdata_int = 8'b0;
    add_i = 2'b00;
    repeat (2) @(posedge pclk);
    preset_n = 1'b1;
    repeat (2) @(posedge pclk);

// 1st test - set, start, stop the timer
    // set timer
    pwdata_int = 8'b11001000; // 200 stimulses
    paddr_inside = 32'hA000;
    add_i = 2'b11;
    repeat (2) @(posedge pclk);
    add_i = 2'b00;
    repeat (2) @(posedge pclk);

    //start timer
    pwdata_int = 1'b1;
    paddr_inside = 32'hA001;
    add_i = 2'b11;
    repeat (2) @(posedge pclk);
    add_i = 2'b00;
    repeat (50) @(posedge pclk);

    // Stop timer
    pwdata_int = 1'b0;
    add_i = 2'b11;
    repeat (2) @(posedge pclk);
    add_i = 2'b00;
    repeat (4) `CLK;

    // Read
    add_i = 2'b01;
    repeat (2) @(posedge pclk);
    add_i = 2'b00;
    repeat (4) @(posedge pclk);

// 2nd test - start, wait
    //start timer, wait
    pwdata_int = 1'b1;
    add_i = 2'b11;
    repeat (2) @(posedge pclk);
    add_i = 2'b00;
    repeat (200) @(posedge pclk);
    $finish();
  end


  always @(posedge pclk or negedge preset_n)
  begin
    if (~preset_n) begin
      state_q <= 2'b00;
    end else begin
      state_q <= nxt_state;
    end
  end

  always @*
  begin
    nxt_pwrite = pwrite_q;
    nxt_rdata = rdata_q;
    nxt_state = state_q;
    case (state_q)
      2'b00:  // IDLE
        if (add_i[0]) begin
          nxt_state = 2'b01;
          nxt_pwrite = add_i[1];
        end
      2'b01: nxt_state = 2'b10;  // SETUP
      2'b10: // ACCESS
        if (pready_i) begin
          if (~pwrite_q)
            nxt_rdata = prdata_i;
          nxt_state = 2'b00;
        end
    endcase
  end
  
  assign apb_state_access = (state_q == 2'b10);
  assign apb_state_setup = (state_q == 2'b01);
  
  assign psel_o = apb_state_setup | apb_state_access;
  assign penable_o = apb_state_access;
  
  // APB Address
  assign paddr_o = paddr_inside;
  
  // APB PWRITE control signal
  always @(posedge pclk or negedge preset_n)
    if (~preset_n)
      pwrite_q <= 1'b0;
    else
      pwrite_q <= nxt_pwrite;
  
  assign pwrite_o = pwrite_q;
  assign pwdata_o = pwdata_int;

  always @(posedge pclk or negedge preset_n)
    if (~preset_n)
      rdata_q <= 8'b0;
    else
      rdata_q <= nxt_rdata;


  // VCD Dump
  initial begin
    $dumpfile("apb_master.vcd");
    $dumpvars(2, apb_master_tb);
  end

endmodule

apb_master.vcd
$date
	Tue Jun 04 13:18:22 2024
$end
$version
	Icarus Verilog
$end
$timescale
	1s
$end
$scope module apb_master_tb $end
$var wire 1 ! apb_state_access $end
$var wire 1 " apb_state_setup $end
$var wire 32 # paddr_o [31:0] $end
$var wire 1 $ penable_o $end
$var wire 8 % prdata_i [7:0] $end
$var wire 1 & pready_i $end
$var wire 1 ' psel_o $end
$var wire 8 ( pwdata_o [7:0] $end
$var wire 1 ) pwrite_o $end
$var wire 1 * timeout $end
$var reg 2 + add_i [1:0] $end
$var reg 1 , nxt_pwrite $end
$var reg 8 - nxt_rdata [7:0] $end
$var reg 2 . nxt_state [1:0] $end
$var reg 32 / paddr_inside [31:0] $end
$var reg 1 0 pclk $end
$var reg 1 1 preset_n $end
$var reg 8 2 pwdata_int [7:0] $end
$var reg 1 3 pwrite_q $end
$var reg 8 4 rdata_q [7:0] $end
$var reg 2 5 state_q [1:0] $end
$scope module APB_SLAVE $end
$var wire 32 6 paddr_o [31:0] $end
$var wire 1 7 pclk $end
$var wire 1 $ penable_o $end
$var wire 8 8 prdata_i [7:0] $end
$var wire 1 & pready_i $end
$var wire 1 9 preset_n $end
$var wire 1 ' psel_o $end
$var wire 8 : pwdata_o [7:0] $end
$var wire 1 ) pwrite_o $end
$var wire 1 * timeout $end
$var reg 8 ; counter [7:0] $end
$var reg 1 < is_timeout $end
$var reg 8 = prdata_ii [7:0] $end
$var reg 1 > pready_ii $end
$var reg 1 ? start_stop $end
$upscope $end
$upscope $end
$enddefinitions $end
#0
$dumpvars
0?
0>
bx =
0<
b0 ;
b0 :
09
bx 8
07
bx 6
bx 5
bx 4
x3
b0 2
01
00
bx /
bx .
bx -
x,
b0 +
0*
x)
b0 (
x'
0&
bx %
x$
bx #
x"
x!
$end
#5
0'
b0 .
b0 -
0,
b0 5
0!
0$
0"
03
0)
b0 4
10
17
#10
00
07
#15
11
19
10
17
#20
00
07
#25
10
17
#30
00
07
#35
1,
b1 .
b11 +
b1010000000000000 /
b1010000000000000 #
b1010000000000000 6
b11001000 2
b11001000 (
b11001000 :
10
17
#40
00
07
#45
1'
b10 .
b1 5
1"
13
1)
10
17
#50
00
07
#55
b10 5
1!
1$
0"
b10 .
b0 +
10
17
#60
00
07
#65
b0 .
b11001000 ;
1>
1&
10
17
#70
00
07
#75
0'
1?
b0 5
0!
0$
b1 .
b11 +
b1010000000000001 /
b1010000000000001 #
b1010000000000001 6
b1 2
b1 (
b1 :
10
17
#80
00
07
#85
1'
b10 .
b1 5
1"
0>
0&
b11000111 ;
10
17
#90
00
07
#95
b11000110 ;
b10 5
1!
1$
0"
b10 .
b0 +
10
17
#100
00
07
#105
b0 .
1>
1&
b11000101 ;
10
17
#110
00
07
#115
0'
b11000100 ;
b0 5
0!
0$
10
17
#120
00
07
#125
0>
0&
b11000011 ;
10
17
#130
00
07
#135
b11000010 ;
10
17
#140
00
07
#145
b11000001 ;
10
17
#150
00
07
#155
b11000000 ;
10
17
#160
00
07
#165
b10111111 ;
10
17
#170
00
07
#175
b10111110 ;
10
17
#180
00
07
#185
b10111101 ;
10
17
#190
00
07
#195
b10111100 ;
10
17
#200
00
07
#205
b10111011 ;
10
17
#210
00
07
#215
b10111010 ;
10
17
#220
00
07
#225
b10111001 ;
10
17
#230
00
07
#235
b10111000 ;
10
17
#240
00
07
#245
b10110111 ;
10
17
#250
00
07
#255
b10110110 ;
10
17
#260
00
07
#265
b10110101 ;
10
17
#270
00
07
#275
b10110100 ;
10
17
#280
00
07
#285
b10110011 ;
10
17
#290
00
07
#295
b10110010 ;
10
17
#300
00
07
#305
b10110001 ;
10
17
#310
00
07
#315
b10110000 ;
10
17
#320
00
07
#325
b10101111 ;
10
17
#330
00
07
#335
b10101110 ;
10
17
#340
00
07
#345
b10101101 ;
10
17
#350
00
07
#355
b10101100 ;
10
17
#360
00
07
#365
b10101011 ;
10
17
#370
00
07
#375
b10101010 ;
10
17
#380
00
07
#385
b10101001 ;
10
17
#390
00
07
#395
b10101000 ;
10
17
#400
00
07
#405
b10100111 ;
10
17
#410
00
07
#415
b10100110 ;
10
17
#420
00
07
#425
b10100101 ;
10
17
#430
00
07
#435
b10100100 ;
10
17
#440
00
07
#445
b10100011 ;
10
17
#450
00
07
#455
b10100010 ;
10
17
#460
00
07
#465
b10100001 ;
10
17
#470
00
07
#475
b10100000 ;
10
17
#480
00
07
#485
b10011111 ;
10
17
#490
00
07
#495
b10011110 ;
10
17
#500
00
07
#505
b10011101 ;
10
17
#510
00
07
#515
b10011100 ;
10
17
#520
00
07
#525
b10011011 ;
10
17
#530
00
07
#535
b10011010 ;
10
17
#540
00
07
#545
b10011001 ;
10
17
#550
00
07
#555
b10011000 ;
10
17
#560
00
07
#565
b10010111 ;
10
17
#570
00
07
#575
b10010110 ;
10
17
#580
00
07
#585
b10010101 ;
10
17
#590
00
07
#595
b10010100 ;
b1 .
b11 +
b0 2
b0 (
b0 :
10
17
#600
00
07
#605
b10 .
1'
b1 5
1"
b10010011 ;
10
17
#610
00
07
#615
b10010010 ;
b10 5
1!
1$
0"
b10 .
b0 +
10
17
#620
00
07
#625
b0 .
0?
1>
1&
b10010001 ;
10
17
#630
00
07
#635
0'
b0 5
0!
0$
10
17
#640
00
07
#645
0>
0&
10
17
#650
00
07
#655
0,
b1 .
b1 +
10
17
#660
00
07
#665
1'
b10 .
b1 5
1"
03
0)
10
17
#670
00
07
#675
b10 5
1!
1$
0"
b10 .
b0 +
10
17
#680
00
07
#685
b0 .
b10010001 -
b10010001 =
b10010001 %
b10010001 8
1>
1&
10
17
#690
00
07
#695
0'
b10010001 4
b0 5
0!
0$
10
17
#700
00
07
#705
0>
0&
10
17
#710
00
07
#715
1,
b1 .
b11 +
b1 2
b1 (
b1 :
10
17
#720
00
07
#725
1'
b10 .
b1 5
1"
13
1)
10
17
#730
00
07
#735
b10 5
1!
1$
0"
b10 .
b0 +
10
17
#740
00
07
#745
b0 .
1?
1>
1&
10
17
#750
00
07
#755
0'
b10010000 ;
b0 5
0!
0$
10
17
#760
00
07
#765
0>
0&
b10001111 ;
10
17
#770
00
07
#775
b10001110 ;
10
17
#780
00
07
#785
b10001101 ;
10
17
#790
00
07
#795
b10001100 ;
10
17
#800
00
07
#805
b10001011 ;
10
17
#810
00
07
#815
b10001010 ;
10
17
#820
00
07
#825
b10001001 ;
10
17
#830
00
07
#835
b10001000 ;
10
17
#840
00
07
#845
b10000111 ;
10
17
#850
00
07
#855
b10000110 ;
10
17
#860
00
07
#865
b10000101 ;
10
17
#870
00
07
#875
b10000100 ;
10
17
#880
00
07
#885
b10000011 ;
10
17
#890
00
07
#895
b10000010 ;
10
17
#900
00
07
#905
b10000001 ;
10
17
#910
00
07
#915
b10000000 ;
10
17
#920
00
07
#925
b1111111 ;
10
17
#930
00
07
#935
b1111110 ;
10
17
#940
00
07
#945
b1111101 ;
10
17
#950
00
07
#955
b1111100 ;
10
17
#960
00
07
#965
b1111011 ;
10
17
#970
00
07
#975
b1111010 ;
10
17
#980
00
07
#985
b1111001 ;
10
17
#990
00
07
#995
b1111000 ;
10
17
#1000
00
07
#1005
b1110111 ;
10
17
#1010
00
07
#1015
b1110110 ;
10
17
#1020
00
07
#1025
b1110101 ;
10
17
#1030
00
07
#1035
b1110100 ;
10
17
#1040
00
07
#1045
b1110011 ;
10
17
#1050
00
07
#1055
b1110010 ;
10
17
#1060
00
07
#1065
b1110001 ;
10
17
#1070
00
07
#1075
b1110000 ;
10
17
#1080
00
07
#1085
b1101111 ;
10
17
#1090
00
07
#1095
b1101110 ;
10
17
#1100
00
07
#1105
b1101101 ;
10
17
#1110
00
07
#1115
b1101100 ;
10
17
#1120
00
07
#1125
b1101011 ;
10
17
#1130
00
07
#1135
b1101010 ;
10
17
#1140
00
07
#1145
b1101001 ;
10
17
#1150
00
07
#1155
b1101000 ;
10
17
#1160
00
07
#1165
b1100111 ;
10
17
#1170
00
07
#1175
b1100110 ;
10
17
#1180
00
07
#1185
b1100101 ;
10
17
#1190
00
07
#1195
b1100100 ;
10
17
#1200
00
07
#1205
b1100011 ;
10
17
#1210
00
07
#1215
b1100010 ;
10
17
#1220
00
07
#1225
b1100001 ;
10
17
#1230
00
07
#1235
b1100000 ;
10
17
#1240
00
07
#1245
b1011111 ;
10
17
#1250
00
07
#1255
b1011110 ;
10
17
#1260
00
07
#1265
b1011101 ;
10
17
#1270
00
07
#1275
b1011100 ;
10
17
#1280
00
07
#1285
b1011011 ;
10
17
#1290
00
07
#1295
b1011010 ;
10
17
#1300
00
07
#1305
b1011001 ;
10
17
#1310
00
07
#1315
b1011000 ;
10
17
#1320
00
07
#1325
b1010111 ;
10
17
#1330
00
07
#1335
b1010110 ;
10
17
#1340
00
07
#1345
b1010101 ;
10
17
#1350
00
07
#1355
b1010100 ;
10
17
#1360
00
07
#1365
b1010011 ;
10
17
#1370
00
07
#1375
b1010010 ;
10
17
#1380
00
07
#1385
b1010001 ;
10
17
#1390
00
07
#1395
b1010000 ;
10
17
#1400
00
07
#1405
b1001111 ;
10
17
#1410
00
07
#1415
b1001110 ;
10
17
#1420
00
07
#1425
b1001101 ;
10
17
#1430
00
07
#1435
b1001100 ;
10
17
#1440
00
07
#1445
b1001011 ;
10
17
#1450
00
07
#1455
b1001010 ;
10
17
#1460
00
07
#1465
b1001001 ;
10
17
#1470
00
07
#1475
b1001000 ;
10
17
#1480
00
07
#1485
b1000111 ;
10
17
#1490
00
07
#1495
b1000110 ;
10
17
#1500
00
07
#1505
b1000101 ;
10
17
#1510
00
07
#1515
b1000100 ;
10
17
#1520
00
07
#1525
b1000011 ;
10
17
#1530
00
07
#1535
b1000010 ;
10
17
#1540
00
07
#1545
b1000001 ;
10
17
#1550
00
07
#1555
b1000000 ;
10
17
#1560
00
07
#1565
b111111 ;
10
17
#1570
00
07
#1575
b111110 ;
10
17
#1580
00
07
#1585
b111101 ;
10
17
#1590
00
07
#1595
b111100 ;
10
17
#1600
00
07
#1605
b111011 ;
10
17
#1610
00
07
#1615
b111010 ;
10
17
#1620
00
07
#1625
b111001 ;
10
17
#1630
00
07
#1635
b111000 ;
10
17
#1640
00
07
#1645
b110111 ;
10
17
#1650
00
07
#1655
b110110 ;
10
17
#1660
00
07
#1665
b110101 ;
10
17
#1670
00
07
#1675
b110100 ;
10
17
#1680
00
07
#1685
b110011 ;
10
17
#1690
00
07
#1695
b110010 ;
10
17
#1700
00
07
#1705
b110001 ;
10
17
#1710
00
07
#1715
b110000 ;
10
17
#1720
00
07
#1725
b101111 ;
10
17
#1730
00
07
#1735
b101110 ;
10
17
#1740
00
07
#1745
b101101 ;
10
17
#1750
00
07
#1755
b101100 ;
10
17
#1760
00
07
#1765
b101011 ;
10
17
#1770
00
07
#1775
b101010 ;
10
17
#1780
00
07
#1785
b101001 ;
10
17
#1790
00
07
#1795
b101000 ;
10
17
#1800
00
07
#1805
b100111 ;
10
17
#1810
00
07
#1815
b100110 ;
10
17
#1820
00
07
#1825
b100101 ;
10
17
#1830
00
07
#1835
b100100 ;
10
17
#1840
00
07
#1845
b100011 ;
10
17
#1850
00
07
#1855
b100010 ;
10
17
#1860
00
07
#1865
b100001 ;
10
17
#1870
00
07
#1875
b100000 ;
10
17
#1880
00
07
#1885
b11111 ;
10
17
#1890
00
07
#1895
b11110 ;
10
17
#1900
00
07
#1905
b11101 ;
10
17
#1910
00
07
#1915
b11100 ;
10
17
#1920
00
07
#1925
b11011 ;
10
17
#1930
00
07
#1935
b11010 ;
10
17
#1940
00
07
#1945
b11001 ;
10
17
#1950
00
07
#1955
b11000 ;
10
17
#1960
00
07
#1965
b10111 ;
10
17
#1970
00
07
#1975
b10110 ;
10
17
#1980
00
07
#1985
b10101 ;
10
17
#1990
00
07
#1995
b10100 ;
10
17
#2000
00
07
#2005
b10011 ;
10
17
#2010
00
07
#2015
b10010 ;
10
17
#2020
00
07
#2025
b10001 ;
10
17
#2030
00
07
#2035
b10000 ;
10
17
#2040
00
07
#2045
b1111 ;
10
17
#2050
00
07
#2055
b1110 ;
10
17
#2060
00
07
#2065
b1101 ;
10
17
#2070
00
07
#2075
b1100 ;
10
17
#2080
00
07
#2085
b1011 ;
10
17
#2090
00
07
#2095
b1010 ;
10
17
#2100
00
07
#2105
b1001 ;
10
17
#2110
00
07
#2115
b1000 ;
10
17
#2120
00
07
#2125
b111 ;
10
17
#2130
00
07
#2135
b110 ;
10
17
#2140
00
07
#2145
b101 ;
10
17
#2150
00
07
#2155
b100 ;
10
17
#2160
00
07
#2165
b11 ;
10
17
#2170
00
07
#2175
b10 ;
10
17
#2180
00
07
#2185
b1 ;
10
17
#2190
00
07
#2195
b0 ;
10
17
#2200
00
07
#2205
1<
1*
10
17
